{"errors":[],"warnings":[],"namedChunkGroups":{"app":{"chunks":[6,0,3],"assets":["webpack-runtime-5a3a9fdbe9922c47c1bb.js","webpack-runtime-5a3a9fdbe9922c47c1bb.js.map","styles.c66b96b7fc1479973378.css","styles-dd330291022e26c5ff5a.js","styles-dd330291022e26c5ff5a.js.map","app-594b97a070166b17813c.js","app-594b97a070166b17813c.js.map"],"children":{},"childAssets":{}},"component---src-pages-index-js":{"chunks":[0,7,4],"assets":["styles.c66b96b7fc1479973378.css","styles-dd330291022e26c5ff5a.js","styles-dd330291022e26c5ff5a.js.map","7-691bb6f14b03d688daf0.js","7-691bb6f14b03d688daf0.js.map","component---src-pages-index-js-688149a238654d66d97d.js","component---src-pages-index-js-688149a238654d66d97d.js.map"],"children":{},"childAssets":{}},"pages-manifest":{"chunks":[5],"assets":["pages-manifest-3138e7b3690555f1c201.js","pages-manifest-3138e7b3690555f1c201.js.map"],"children":{},"childAssets":{}}},"assetsByChunkName":{"app":["webpack-runtime-5a3a9fdbe9922c47c1bb.js","styles.c66b96b7fc1479973378.css","styles-dd330291022e26c5ff5a.js","app-594b97a070166b17813c.js"],"component---src-pages-index-js":["styles.c66b96b7fc1479973378.css","styles-dd330291022e26c5ff5a.js","7-691bb6f14b03d688daf0.js","component---src-pages-index-js-688149a238654d66d97d.js"],"pages-manifest":["pages-manifest-3138e7b3690555f1c201.js"]}}